Metadata-Version: 1.1
Name: eclyssia
Version: 1.2.1
Summary: An eclyssia-api wrapper built for python3+
Home-page: https://github.com/Zenrac/eclyssia.py
Author: Zenrac
Author-email: zenrac@outlook.fr
License: UNKNOWN
Download-URL: https://github.com/Zenrac/eclyssia.py/archive/1.2.1.tar.gz
Keywords: eclyssia
Platform: UNKNOWN
